libri_light_dtw.cpython-38-x86_64-linux-gnu.so
zerospeech_libriabx-1.0.5.dist-info/top_level.txt
zerospeech_libriabx-1.0.5.dist-info/WHEEL
zerospeech_libriabx-1.0.5.dist-info/entry_points.txt
zerospeech_libriabx-1.0.5.dist-info/LICENCE.txt
zerospeech_libriabx-1.0.5.dist-info/RECORD
zerospeech_libriabx-1.0.5.dist-info/METADATA
libriabx/wrappers.py
libriabx/__init__.py
libriabx/libri_light/CPC_loader.py
libriabx/libri_light/README.md
libriabx/libri_light/eval_ABX.py
libriabx/libri_light/LICENCE.txt
libriabx/libri_light/__init__.py
libriabx/libri_light/ABX_src/abx_group_computation.py
libriabx/libri_light/ABX_src/dtw.pyx
libriabx/libri_light/ABX_src/dtw.c
libriabx/libri_light/ABX_src/abx_iterators.py
libriabx/libri_light/ABX_src/__init__.py
