Metadata-Version: 2.1
Name: zerospeech-libriabx
Version: 1.0.5
Summary: Wrapper package for librilight-abx.
Author-email: Nicolas Hamilakis <nicolas.hamilakis@ens.psl.eu>, CoML Team <dev@zerospeech.com>
Project-URL: documentation, https://zerospeech.com/toolbox/
Project-URL: homepage, https://zerospeech.com/
Project-URL: repository, https://github.com/zerospeech/libri-light-abx
Keywords: speech,machine-learning,challenges,research-tool,benchmark-speech,zerospeech
Classifier: Topic :: Scientific/Engineering :: Artificial Intelligence
Classifier: Intended Audience :: Science/Research
Requires-Python: >=3.8
License-File: LICENCE.txt
Requires-Dist: torch
Requires-Dist: progressbar2
Requires-Dist: torchaudio
Requires-Dist: numpy
Requires-Dist: virtual-dataset
Provides-Extra: dev
Requires-Dist: ipython ; extra == 'dev'
Requires-Dist: pytest ; extra == 'dev'
Requires-Dist: twine ; extra == 'dev'
Requires-Dist: build ; extra == 'dev'
